fast_x402/__init__.py
fast_x402/cli.py
fast_x402/dashboard.py
fast_x402/dependencies.py
fast_x402/development.py
fast_x402/enhanced_network.py
fast_x402/enhanced_provider.py
fast_x402/exceptions.py
fast_x402/logger.py
fast_x402/middleware.py
fast_x402/models.py
fast_x402/network.py
fast_x402/provider.py
fast_x402/rpc_manager.py
fast_x402/security.py
fast_x402/verification.py
fast_x402/shared/__init__.py
fast_x402/shared/analytics.py
fast_x402/shared/facilitator.py
fast_x402/shared/wallet.py
fast_x402-1.3.0.dist-info/METADATA
fast_x402-1.3.0.dist-info/WHEEL
fast_x402-1.3.0.dist-info/entry_points.txt
fast_x402-1.3.0.dist-info/top_level.txt
fast_x402-1.3.0.dist-info/RECORD
