Metadata-Version: 2.1
Name: fast-x402
Version: 1.3.0
Summary: Lightning-fast x402 payment integration for FastAPI and modern Python web frameworks
Home-page: https://github.com/x402/fast-x402
Author: x402 Team
Author-email: support@x402.org
Project-URL: Bug Tracker, https://github.com/x402/fast-x402/issues
Project-URL: Documentation, https://docs.x402.org/fast-x402
Project-URL: Source Code, https://github.com/x402/fast-x402
Keywords: x402,payments,micropayments,fastapi,http402,blockchain,stablecoin,api-monetization
Classifier: Development Status :: 4 - Beta
Classifier: Intended Audience :: Developers
Classifier: Topic :: Software Development :: Libraries :: Python Modules
Classifier: Topic :: Internet :: WWW/HTTP :: HTTP Servers
Classifier: Topic :: Office/Business :: Financial :: Point-Of-Sale
Classifier: License :: OSI Approved :: MIT License
Classifier: Programming Language :: Python :: 3
Classifier: Programming Language :: Python :: 3.9
Classifier: Programming Language :: Python :: 3.10
Classifier: Programming Language :: Python :: 3.11
Classifier: Framework :: FastAPI
Classifier: Operating System :: OS Independent
Requires-Python: >=3.9
Requires-Dist: fastapi >=0.100.0
Requires-Dist: eth-account <0.11.0,>=0.10.0
Requires-Dist: web3 >=6.11.0
Requires-Dist: pydantic >=2.0.0
Requires-Dist: httpx >=0.24.0
Requires-Dist: redis >=4.5.0
Requires-Dist: click >=8.0.0
Requires-Dist: rich >=13.0.0
Requires-Dist: mnemonic >=0.20
Requires-Dist: uvicorn >=0.24.0
Provides-Extra: cli
Requires-Dist: click >=8.0.0 ; extra == 'cli'
Requires-Dist: rich >=13.0.0 ; extra == 'cli'
Provides-Extra: dev
Requires-Dist: pytest >=7.4.0 ; extra == 'dev'
Requires-Dist: pytest-asyncio >=0.21.0 ; extra == 'dev'
Requires-Dist: pytest-cov >=4.1.0 ; extra == 'dev'
Requires-Dist: black >=23.7.0 ; extra == 'dev'
Requires-Dist: ruff >=0.0.286 ; extra == 'dev'
Requires-Dist: mypy >=1.5.0 ; extra == 'dev'
Requires-Dist: uvicorn >=0.24.0 ; extra == 'dev'
